edgar_tool/__init__.py
edgar_tool/__main__.py
edgar_tool/cli.py
edgar_tool/constants.py
edgar_tool/io.py
edgar_tool/location_autocomplete.py
edgar_tool/rss.py
edgar_tool/search_params.py
edgar_tool/text_search.py
edgar_tool/url_generator.py
edgar_tool/utils.py
edgar_tool-2.1.2.dist-info/LICENSE
edgar_tool-2.1.2.dist-info/METADATA
edgar_tool-2.1.2.dist-info/WHEEL
edgar_tool-2.1.2.dist-info/entry_points.txt
edgar_tool-2.1.2.dist-info/RECORD
