Metadata-Version: 2.3
Name: edgar-tool
Version: 2.1.2
Summary: Search and retrieve corporate and financial data from the United States Securities and Exchange Commission (SEC).
License: GNU General Public License v3 (GPLv3)
Keywords: scraper,edgar,finance,sec
Author: Bellingcat
Author-email: contact@bellingcat.com
Maintainer: Jordan Gillard
Maintainer-email: jordan@gaproject.com
Requires-Python: >=3.9
Classifier: Development Status :: 5 - Production/Stable
Classifier: Intended Audience :: Developers
Classifier: Intended Audience :: Financial and Insurance Industry
Classifier: Intended Audience :: Science/Research
Classifier: License :: Other/Proprietary License
Classifier: Programming Language :: Python :: 3
Classifier: Programming Language :: Python :: 3.9
Classifier: Programming Language :: Python :: 3.10
Classifier: Programming Language :: Python :: 3.11
Classifier: Programming Language :: Python :: 3.12
Classifier: Programming Language :: Python :: 3.13
Classifier: Topic :: Office/Business :: Financial
Requires-Dist: click (>=8.1.7,<8.2.0)
Requires-Dist: jsonlines (>=4.0,<5.0)
Requires-Dist: pydantic (>=2.10.5,<3.0.0)
Requires-Dist: pytest (>=8.2.2,<9.0.0)
Requires-Dist: python-dateutil (>=2.9.0.post0,<3.0.0)
Requires-Dist: requests (>=2.31,<3.0)
Requires-Dist: tenacity (>=8.2,<9.0)
Requires-Dist: typer (>=0.12.5,<0.13.0)
Requires-Dist: xmltodict (>=0.13,<0.14)
Project-URL: Issues, https://github.com/bellingcat/EDGAR/issues
Project-URL: Repository, https://github.com/bellingcat/EDGAR
